<?xml version="1.0" encoding="UTF-8" standalone="yes"?>
<SharedFlowBundle revision="23" name="api_wise_spike_quota">
    <ConfigurationVersion majorVersion="4" minorVersion="0"/>
    <CreatedAt>1684844798324</CreatedAt>
    <CreatedBy>ban320841@ext.icicibank.com</CreatedBy>
    <Description>api_wise_spike_quota</Description>
    <DisplayName>api_wise_spike_quota</DisplayName>
    <LastModifiedAt>1761553810548</LastModifiedAt>
    <LastModifiedBy>papul.khapekar@ext.icicibank.com</LastModifiedBy>
    <ManifestVersion>SHA-512:bf3f6a232f5be1906b88affeed1a19570efcc555b0348ac28c1d883691eba65a9503e9a7eae0182922198bad7f9de548c0cbc3cbe16ebebc77bfec1ce78fa238:ap-northeast-1</ManifestVersion>
    <Policies>
        <Policy>AM-Quota-Consumption-Details</Policy>
        <Policy>JS-MonetizationAttributes</Policy>
        <Policy>JS-QuotaDailycheckConsumption</Policy>
        <Policy>JS-setKey</Policy>
        <Policy>JS-setVariables</Policy>
        <Policy>JS-setVariablesMerchantwise</Policy>
        <Policy>KVM-icici_api_wise_spike_quota</Policy>
        <Policy>KVM-icici_merchant_wise_spike_quota</Policy>
        <Policy>ML-Daily</Policy>
        <Policy>ML-MerchantWiseDaily</Policy>
        <Policy>ML-merchantapilevel</Policy>
        <Policy>MLC-Monetization</Policy>
        <Policy>Q-Daily</Policy>
        <Policy>Q-MerchantWiseDaily</Policy>
        <Policy>RF-MerchantWiseDaily</Policy>
        <Policy>RF-MonetizationFailed</Policy>
        <Policy>RF-QuotaDaily</Policy>
        <Policy>RF-SpikeArrest</Policy>
        <Policy>RF-SpikeArrestMerchant</Policy>
        <Policy>SA-apilevel</Policy>
        <Policy>SA-merchantapilevel</Policy>
        <Policy>SC_CHECK_LOG</Policy>
    </Policies>
    <Resources>
        <Resource>jsc://JS-MonetizationAttributes.js</Resource>
        <Resource>jsc://JS-QuotaDailycheckConsumption.js</Resource>
        <Resource>jsc://JS-setKey.js</Resource>
        <Resource>jsc://JS-setVariables.js</Resource>
        <Resource>jsc://JS-setVariablesMerchantwise.js</Resource>
    </Resources>
    <Spec></Spec>
    <subType>SharedFlow</subType>
    <SharedFlows>
        <SharedFlow>default</SharedFlow>
    </SharedFlows>
</SharedFlowBundle>
